{"nodes": [{"id": "d_coding_clients_iva_designers_main_iva_designers_main_src_lib_repositories_devices_ts", "label": "devices.ts", "file_type": "code", "source_file": "D:\\coding\\Clients\\IVA-Designers-main\\IVA-Designers-main\\src\\lib\\repositories\\devices.ts", "source_location": "L1"}, {"id": "devices_requestdevicereset", "label": "requestDeviceReset()", "file_type": "code", "source_file": "D:\\coding\\Clients\\IVA-Designers-main\\IVA-Designers-main\\src\\lib\\repositories\\devices.ts", "source_location": "L4"}], "edges": [{"source": "d_coding_clients_iva_designers_main_iva_designers_main_src_lib_repositories_devices_ts", "target": "db", "relation": "imports_from", "confidence": "EXTRACTED", "source_file": "D:\\coding\\Clients\\IVA-Designers-main\\IVA-Designers-main\\src\\lib\\repositories\\devices.ts", "source_location": "L1", "weight": 1.0}, {"source": "d_coding_clients_iva_designers_main_iva_designers_main_src_lib_repositories_devices_ts", "target": "env", "relation": "imports_from", "confidence": "EXTRACTED", "source_file": "D:\\coding\\Clients\\IVA-Designers-main\\IVA-Designers-main\\src\\lib\\repositories\\devices.ts", "source_location": "L2", "weight": 1.0}, {"source": "d_coding_clients_iva_designers_main_iva_designers_main_src_lib_repositories_devices_ts", "target": "devices_requestdevicereset", "relation": "contains", "confidence": "EXTRACTED", "source_file": "D:\\coding\\Clients\\IVA-Designers-main\\IVA-Designers-main\\src\\lib\\repositories\\devices.ts", "source_location": "L4", "weight": 1.0}], "raw_calls": [{"caller_nid": "devices_requestdevicereset", "callee": "updateMany", "source_file": "D:\\coding\\Clients\\IVA-Designers-main\\IVA-Designers-main\\src\\lib\\repositories\\devices.ts", "source_location": "L15"}, {"caller_nid": "devices_requestdevicereset", "callee": "now", "source_file": "D:\\coding\\Clients\\IVA-Designers-main\\IVA-Designers-main\\src\\lib\\repositories\\devices.ts", "source_location": "L19"}]}